django_admin_conf_vars/__init__.py
django_admin_conf_vars/admin.py
django_admin_conf_vars/apps.py
django_admin_conf_vars/global_vars.py
django_admin_conf_vars/models.py
django_admin_conf_vars/tests.py
django_admin_conf_vars/views.py
django_admin_conf_vars/migrations/0001_initial.py
django_admin_conf_vars/migrations/0002_auto_20150413_2238.py
django_admin_conf_vars/migrations/0003_configurationvariable_editable.py
django_admin_conf_vars/migrations/0004_configurationvariable_description.py
django_admin_conf_vars/migrations/0005_auto_20180725_1624.py
django_admin_conf_vars/migrations/__init__.py
django_admin_conf_vars-0.4.1.dist-info/METADATA
django_admin_conf_vars-0.4.1.dist-info/RECORD
django_admin_conf_vars-0.4.1.dist-info/WHEEL
django_admin_conf_vars-0.4.1.dist-info/top_level.txt
